bse/BSE.py
bse/__init__.py
bse/constants.py
bse-3.0.2.dist-info/METADATA
bse-3.0.2.dist-info/WHEEL
bse-3.0.2.dist-info/licenses/LICENSE
bse-3.0.2.dist-info/RECORD
